Metadata-Version: 2.1
Name: text-file-splitter
Version: 0.0.13
Summary: Python module to split files fast and easy
Home-page: https://github.com/juancarlosjr97/text-file-splitter
Author: Juan Carlos Blanco Delgado
Author-email: juancarlosjr97@gmail.com
License: MIT
Download-URL: https://github.com/juancarlosjr97/text-file-splitter/dist/text-file-splitter-0.0.13.tar.gz
Keywords: csv split splitter
Platform: UNKNOWN
Classifier: Programming Language :: Python :: 3.4
Classifier: Programming Language :: Python :: 3.5
Classifier: Programming Language :: Python :: 3.6
Classifier: Programming Language :: Python :: 3.7
